colaburl/__init__.py
colaburl/server.py
tests/__init__.py
tests/test_colaburl.py
colaburl-0.1.0.dist-info/LICENSE
colaburl-0.1.0.dist-info/METADATA
colaburl-0.1.0.dist-info/WHEEL
colaburl-0.1.0.dist-info/top_level.txt
colaburl-0.1.0.dist-info/RECORD
