Metadata-Version: 2.1
Name: colaburl
Version: 0.1.0
Summary: Colab URL Generator from Code
Home-page: https://github.com/seanmacavaney/colaburl
Author: Sean MacAvaney
Author-email: sean.macavaney@glasgow.ac.uk
Requires-Python: >=3.7
License-File: LICENSE
Requires-Dist: lz4
